setup.py
php_wsgi/__init__.py
php_wsgi/php_app.py
php_wsgi/tests.py
php_wsgi.egg-info/PKG-INFO
php_wsgi.egg-info/SOURCES.txt
php_wsgi.egg-info/dependency_links.txt
php_wsgi.egg-info/requires.txt
php_wsgi.egg-info/top_level.txt