Metadata-Version: 1.0
Name: php-wsgi
Version: 0.0.8
Summary: run php from python
Home-page: UNKNOWN
Author: Kyle Roux
Author-email: kyle@level2designs.com
License: UNKNOWN
Platform: UNKNOWN
